{
  "buildCommand" : {
    "command" : "build",
    "skipDependencies" : false,
    "style" : "buildAndRun"
  },
  "configuredTargets" : [
    {
      "guid" : "1f8f2cfa1301f7281fd453dc46d8b94bc17df18f254404d99b8779d1e19a1b49"
    }
  ],
  "containerPath" : "/Users/meguty/Develop/Soko/Sokoban/Sokoban.xcodeproj",
  "continueBuildingAfterErrors" : false,
  "dependencyScope" : "workspace",
  "enableIndexBuildArena" : false,
  "hideShellScriptEnvironment" : false,
  "parameters" : {
    "action" : "build",
    "configurationName" : "Debug",
    "overrides" : {
      "commandLine" : {
        "table" : {
          "SDKROOT" : "iphonesimulator26.2"
        }
      },
      "synthesized" : {
        "table" : {
          "ACTION" : "build",
          "ENABLE_PREVIEWS" : "NO",
          "ENABLE_XOJIT_PREVIEWS" : "NO"
        }
      }
    }
  },
  "showNonLoggedProgress" : true,
  "useDryRun" : false,
  "useImplicitDependencies" : false,
  "useLegacyBuildLocations" : false,
  "useParallelTargets" : true
}